{
  "data": [
    {
      "type": "vehicle",
      "id": "595449dc-59b8-400c-9d8c-ae03cab9163b",
      "attributes": {
        "state": "ACTIVE",
        "lastLocationUpdate": "2021-12-16T09:36:00Z",
        "lastStateChange": "2021-12-09T12:12:01Z",
        "batteryLevel": 22,
        "lat": 52.510323,
        "lng": 13.499729,
        "maxSpeed": 20,
        "zoneId": "BERLIN",
        "code": 293401,
        "iotVendor": "okai",
        "licencePlate": "288WNG",
        "isRentable": true,
        "vehicleType": "escooter",
        "hasHelmetBox": false,
        "hasHelmet": false
      }
    },
    {
      "type": "vehicle",
      "id": "3a590751-72a3-4f8b-90cb-d7f638b5756e",
      "attributes": {
        "state": "ACTIVE",
        "lastLocationUpdate": "2021-12-16T09:38:31Z",
        "lastStateChange": "2021-12-09T12:12:01Z",
        "batteryLevel": 32,
        "lat": 52.510272,
        "lng": 13.499283,
        "maxSpeed": 20,
        "zoneId": "BERLIN",
        "code": 289701,
        "iotVendor": "okai",
        "licencePlate": "570WMU",
        "isRentable": true,
        "vehicleType": "escooter",
        "hasHelmetBox": false,
        "hasHelmet": false
      }
    },
    {
      "type": "vehicle",
      "id": "71bbaa4a-0a28-4295-8f35-74981cc057e8",
      "attributes": {
        "state": "ACTIVE",
        "lastLocationUpdate": "2021-12-16T09:42:41Z",
        "lastStateChange": "2021-12-12T10:25:15Z",
        "batteryLevel": 33,
        "lat": 52.510193,
        "lng": 13.499248,
        "maxSpeed": 20,
        "zoneId": "BERLIN",
        "code": 212837,
        "iotVendor": "okai",
        "licencePlate": "368YTP",
        "isRentable": true,
        "vehicleType": "escooter",
        "hasHelmetBox": false,
        "hasHelmet": false
      }
    },
    {
      "type": "vehicle",
      "id": "552e17a5-2eea-4011-ba9f-494dd45e7af1",
      "attributes": {
        "state": "ACTIVE",
        "lastLocationUpdate": "2021-12-16T09:40:12Z",
        "lastStateChange": "2021-12-13T00:45:27Z",
        "batteryLevel": 75,
        "lat": 52.510325,
        "lng": 13.499315,
        "maxSpeed": 20,
        "zoneId": "BERLIN",
        "code": 294405,
        "iotVendor": "okai",
        "licencePlate": "878WMX",
        "isRentable": true,
        "vehicleType": "escooter",
        "hasHelmetBox": false,
        "hasHelmet": false
      }
    }
  ]
}
