[
  {
    "tripId": "1|40768|10|86|26042022",
    "stop": {
      "type": "stop",
      "id": "900000160004",
      "name": "S+U Lichtenberg",
      "location": {
        "type": "location",
        "id": "900160004",
        "latitude": 52.510676,
        "longitude": 13.498355
      },
      "products": {
        "suburban": true,
        "subway": true,
        "tram": true,
        "bus": true,
        "ferry": false,
        "express": true,
        "regional": true
      }
    },
    "when": null,
    "plannedWhen": "2022-04-26T17:48:00+02:00",
    "prognosedWhen": null,
    "delay": null,
    "platform": null,
    "plannedPlatform": null,
    "prognosedPlatform": null,
    "direction": null,
    "provenance": "S Mahlsdorf",
    "line": {
      "type": "line",
      "id": "s5",
      "fahrtNr": "19876",
      "name": "S5",
      "public": true,
      "adminCode": "DBS",
      "productName": "S",
      "mode": "train",
      "product": "suburban",
      "operator": {
        "type": "operator",
        "id": "s-bahn-berlin-gmbh",
        "name": "S-Bahn Berlin GmbH"
      },
      "symbol": "S",
      "nr": 5,
      "metro": false,
      "express": false,
      "night": false
    },
    "remarks": [
      {
        "type": "hint",
        "code": "bf",
        "text": "barrier-free"
      },
      {
        "type": "hint",
        "code": "FB",
        "text": "Bicycle conveyance"
      },
      {
        "id": "163090",
        "type": "warning",
        "summary": "Störung.",
        "text": "Nach einem beendeten Polizeieinsatz Warschauer Str. und Westkreuz verkehren die Züge der S5 noch unregelmäßig . Die zusätzlichen Züge zwischen Mahlsdorf und Ostbahnhof verkehren nicht.",
        "icon": {
          "type": "HIM2",
          "title": null
        },
        "priority": 50,
        "products": {
          "suburban": true,
          "subway": true,
          "tram": true,
          "bus": true,
          "ferry": true,
          "express": true,
          "regional": true
        },
        "company": "VBB",
        "categories": [
          2
        ],
        "validFrom": "2022-04-26T15:00:00+02:00",
        "validUntil": "2022-04-26T23:59:00+02:00",
        "modified": "2022-04-26T16:55:48+02:00"
      },
      {
        "id": "144719",
        "type": "warning",
        "summary": "Masks are mandatory!",
        "text": "Please wear an FFP2 mask in the vehicles.\n<a href=\"https://www.vbb.de/corona\" target=\"_blank\" rel=\"noopener\">Further information (in German language)</a>",
        "icon": {
          "type": "HIM0",
          "title": null
        },
        "priority": 100,
        "products": {
          "suburban": true,
          "subway": true,
          "tram": true,
          "bus": true,
          "ferry": true,
          "express": true,
          "regional": true
        },
        "company": "VBB",
        "categories": [
          0
        ],
        "validFrom": "2021-11-24T00:00:00+01:00",
        "validUntil": "2022-12-31T00:00:00+01:00",
        "modified": "2022-04-01T06:48:49+02:00"
      },
      {
        "type": "status",
        "code": "text.realtime.journey.cancelled",
        "text": "S5 has been cancelled"
      },
      {
        "type": "status",
        "code": "text.realtime.stop.cancelled",
        "text": "Stop cancelled"
      }
    ],
    "origin": null,
    "destination": null,
    "cancelled": true
  },
  {
    "tripId": "1|40770|11|86|26042022",
    "stop": {
      "type": "stop",
      "id": "900000160004",
      "name": "S+U Lichtenberg",
      "location": {
        "type": "location",
        "id": "900160004",
        "latitude": 52.510676,
        "longitude": 13.498355
      },
      "products": {
        "suburban": true,
        "subway": true,
        "tram": true,
        "bus": true,
        "ferry": false,
        "express": true,
        "regional": true
      }
    },
    "when": null,
    "plannedWhen": "2022-04-26T17:55:00+02:00",
    "prognosedWhen": null,
    "delay": null,
    "platform": null,
    "plannedPlatform": null,
    "prognosedPlatform": null,
    "direction": null,
    "provenance": "S Ostbahnhof",
    "line": {
      "type": "line",
      "id": "s5",
      "fahrtNr": "19857",
      "name": "S5",
      "public": true,
      "adminCode": "DBS",
      "productName": "S",
      "mode": "train",
      "product": "suburban",
      "operator": {
        "type": "operator",
        "id": "s-bahn-berlin-gmbh",
        "name": "S-Bahn Berlin GmbH"
      },
      "symbol": "S",
      "nr": 5,
      "metro": false,
      "express": false,
      "night": false
    },
    "remarks": [
      {
        "type": "hint",
        "code": "bf",
        "text": "barrier-free"
      },
      {
        "type": "hint",
        "code": "FB",
        "text": "Bicycle conveyance"
      },
      {
        "id": "163090",
        "type": "warning",
        "summary": "Störung.",
        "text": "Nach einem beendeten Polizeieinsatz Warschauer Str. und Westkreuz verkehren die Züge der S5 noch unregelmäßig . Die zusätzlichen Züge zwischen Mahlsdorf und Ostbahnhof verkehren nicht.",
        "icon": {
          "type": "HIM2",
          "title": null
        },
        "priority": 50,
        "products": {
          "suburban": true,
          "subway": true,
          "tram": true,
          "bus": true,
          "ferry": true,
          "express": true,
          "regional": true
        },
        "company": "VBB",
        "categories": [
          2
        ],
        "validFrom": "2022-04-26T15:00:00+02:00",
        "validUntil": "2022-04-26T23:59:00+02:00",
        "modified": "2022-04-26T16:55:48+02:00"
      },
      {
        "id": "144719",
        "type": "warning",
        "summary": "Masks are mandatory!",
        "text": "Please wear an FFP2 mask in the vehicles.\n<a href=\"https://www.vbb.de/corona\" target=\"_blank\" rel=\"noopener\">Further information (in German language)</a>",
        "icon": {
          "type": "HIM0",
          "title": null
        },
        "priority": 100,
        "products": {
          "suburban": true,
          "subway": true,
          "tram": true,
          "bus": true,
          "ferry": true,
          "express": true,
          "regional": true
        },
        "company": "VBB",
        "categories": [
          0
        ],
        "validFrom": "2021-11-24T00:00:00+01:00",
        "validUntil": "2022-12-31T00:00:00+01:00",
        "modified": "2022-04-01T06:48:49+02:00"
      },
      {
        "type": "status",
        "code": "text.realtime.journey.cancelled",
        "text": "S5 has been cancelled"
      },
      {
        "type": "status",
        "code": "text.realtime.stop.cancelled",
        "text": "Stop cancelled"
      }
    ],
    "origin": null,
    "destination": null,
    "cancelled": true
  },
  {
    "tripId": "1|17320|0|86|26042022",
    "stop": {
      "type": "stop",
      "id": "900000160702",
      "name": "S+U Lichtenberg [Bus]",
      "location": {
        "type": "location",
        "id": "900160702",
        "latitude": 52.510389,
        "longitude": 13.49947
      },
      "products": {
        "suburban": true,
        "subway": true,
        "tram": true,
        "bus": true,
        "ferry": false,
        "express": true,
        "regional": true
      }
    },
    "when": "2022-04-26T17:47:00+02:00",
    "plannedWhen": "2022-04-26T17:48:00+02:00",
    "delay": -60,
    "platform": null,
    "plannedPlatform": null,
    "direction": null,
    "provenance": "S Ostbahnhof",
    "line": {
      "type": "line",
      "id": "240",
      "fahrtNr": "34636",
      "name": "240",
      "public": true,
      "adminCode": "BVB",
      "productName": "Bus",
      "mode": "bus",
      "product": "bus",
      "operator": {
        "type": "operator",
        "id": "berliner-verkehrsbetriebe",
        "name": "Berliner Verkehrsbetriebe"
      },
      "symbol": null,
      "nr": 240,
      "metro": false,
      "express": false,
      "night": false
    },
    "remarks": [
      {
        "type": "hint",
        "code": "bf",
        "text": "barrier-free"
      },
      {
        "id": "144719",
        "type": "warning",
        "summary": "Masks are mandatory!",
        "text": "Please wear an FFP2 mask in the vehicles.\n<a href=\"https://www.vbb.de/corona\" target=\"_blank\" rel=\"noopener\">Further information (in German language)</a>",
        "icon": {
          "type": "HIM0",
          "title": null
        },
        "priority": 100,
        "products": {
          "suburban": true,
          "subway": true,
          "tram": true,
          "bus": true,
          "ferry": true,
          "express": true,
          "regional": true
        },
        "company": "VBB",
        "categories": [
          0
        ],
        "validFrom": "2021-11-24T00:00:00+01:00",
        "validUntil": "2022-12-31T00:00:00+01:00",
        "modified": "2022-04-01T06:48:49+02:00"
      }
    ],
    "origin": null,
    "destination": null,
    "currentTripPosition": {
      "type": "location",
      "latitude": 52.510586,
      "longitude": 13.500306
    }
  },
  {
    "tripId": "1|36772|10|86|26042022",
    "stop": {
      "type": "stop",
      "id": "900000160701",
      "name": "S+U Lichtenberg [U5]",
      "location": {
        "type": "location",
        "id": "900160701",
        "latitude": 52.511135,
        "longitude": 13.498499
      },
      "products": {
        "suburban": true,
        "subway": true,
        "tram": true,
        "bus": true,
        "ferry": false,
        "express": true,
        "regional": true
      }
    },
    "when": "2022-04-26T17:49:00+02:00",
    "plannedWhen": "2022-04-26T17:46:00+02:00",
    "delay": 180,
    "platform": "1",
    "plannedPlatform": "1",
    "direction": null,
    "provenance": "U Hönow",
    "line": {
      "type": "line",
      "id": "u5",
      "fahrtNr": "16090",
      "name": "U5",
      "public": true,
      "adminCode": "BVU",
      "productName": "U",
      "mode": "train",
      "product": "subway",
      "operator": {
        "type": "operator",
        "id": "berliner-verkehrsbetriebe",
        "name": "Berliner Verkehrsbetriebe"
      },
      "symbol": "U",
      "nr": 5,
      "metro": false,
      "express": false,
      "night": false
    },
    "remarks": [
      {
        "type": "hint",
        "code": "bf",
        "text": "barrier-free"
      },
      {
        "type": "hint",
        "code": "FB",
        "text": "Bicycle conveyance"
      },
      {
        "id": "144719",
        "type": "warning",
        "summary": "Masks are mandatory!",
        "text": "Please wear an FFP2 mask in the vehicles.\n<a href=\"https://www.vbb.de/corona\" target=\"_blank\" rel=\"noopener\">Further information (in German language)</a>",
        "icon": {
          "type": "HIM0",
          "title": null
        },
        "priority": 100,
        "products": {
          "suburban": true,
          "subway": true,
          "tram": true,
          "bus": true,
          "ferry": true,
          "express": true,
          "regional": true
        },
        "company": "VBB",
        "categories": [
          0
        ],
        "validFrom": "2021-11-24T00:00:00+01:00",
        "validUntil": "2022-12-31T00:00:00+01:00",
        "modified": "2022-04-01T06:48:49+02:00"
      }
    ],
    "origin": null,
    "destination": null,
    "currentTripPosition": {
      "type": "location",
      "latitude": 52.506568,
      "longitude": 13.512477
    }
  },
  {
    "tripId": "1|17463|3|86|26042022",
    "stop": {
      "type": "stop",
      "id": "900000160702",
      "name": "S+U Lichtenberg [Bus]",
      "location": {
        "type": "location",
        "id": "900160702",
        "latitude": 52.510389,
        "longitude": 13.49947
      },
      "products": {
        "suburban": true,
        "subway": true,
        "tram": true,
        "bus": true,
        "ferry": false,
        "express": true,
        "regional": true
      }
    },
    "when": "2022-04-26T17:49:00+02:00",
    "plannedWhen": "2022-04-26T17:49:00+02:00",
    "delay": 0,
    "platform": null,
    "plannedPlatform": null,
    "direction": null,
    "provenance": "S Storkower Str.",
    "line": {
      "type": "line",
      "id": "240",
      "fahrtNr": "34799",
      "name": "240",
      "public": true,
      "adminCode": "BVB",
      "productName": "Bus",
      "mode": "bus",
      "product": "bus",
      "operator": {
        "type": "operator",
        "id": "berliner-verkehrsbetriebe",
        "name": "Berliner Verkehrsbetriebe"
      },
      "symbol": null,
      "nr": 240,
      "metro": false,
      "express": false,
      "night": false
    },
    "remarks": [
      {
        "type": "hint",
        "code": "bf",
        "text": "barrier-free"
      },
      {
        "id": "144719",
        "type": "warning",
        "summary": "Masks are mandatory!",
        "text": "Please wear an FFP2 mask in the vehicles.\n<a href=\"https://www.vbb.de/corona\" target=\"_blank\" rel=\"noopener\">Further information (in German language)</a>",
        "icon": {
          "type": "HIM0",
          "title": null
        },
        "priority": 100,
        "products": {
          "suburban": true,
          "subway": true,
          "tram": true,
          "bus": true,
          "ferry": true,
          "express": true,
          "regional": true
        },
        "company": "VBB",
        "categories": [
          0
        ],
        "validFrom": "2021-11-24T00:00:00+01:00",
        "validUntil": "2022-12-31T00:00:00+01:00",
        "modified": "2022-04-01T06:48:49+02:00"
      }
    ],
    "origin": null,
    "destination": null,
    "currentTripPosition": {
      "type": "location",
      "latitude": 52.510667,
      "longitude": 13.503883
    }
  },
  {
    "tripId": "1|40872|47|86|26042022",
    "stop": {
      "type": "stop",
      "id": "900000160004",
      "name": "S+U Lichtenberg",
      "location": {
        "type": "location",
        "id": "900160004",
        "latitude": 52.510676,
        "longitude": 13.498355
      },
      "products": {
        "suburban": true,
        "subway": true,
        "tram": true,
        "bus": true,
        "ferry": false,
        "express": true,
        "regional": true
      }
    },
    "when": "2022-04-26T17:50:00+02:00",
    "plannedWhen": "2022-04-26T17:48:00+02:00",
    "delay": 120,
    "platform": "1",
    "plannedPlatform": "1",
    "direction": null,
    "provenance": "S Potsdam Hauptbahnhof",
    "line": {
      "type": "line",
      "id": "s7",
      "fahrtNr": "20404",
      "name": "S7",
      "public": true,
      "adminCode": "DBS",
      "productName": "S",
      "mode": "train",
      "product": "suburban",
      "operator": {
        "type": "operator",
        "id": "s-bahn-berlin-gmbh",
        "name": "S-Bahn Berlin GmbH"
      },
      "symbol": "S",
      "nr": 7,
      "metro": false,
      "express": false,
      "night": false
    },
    "remarks": [
      {
        "type": "hint",
        "code": "bf",
        "text": "barrier-free"
      },
      {
        "type": "hint",
        "code": "FB",
        "text": "Bicycle conveyance"
      },
      {
        "id": "163085",
        "type": "warning",
        "summary": "Störung.",
        "text": "Nach einem Polizeieinsatz (Personen im Gleis) im Bereich Warschauer Str. ist noch mit Verspätungen und vereinzelten Zugausfällen zu rechnen.",
        "icon": {
          "type": "HIM2",
          "title": null
        },
        "priority": 50,
        "products": {
          "suburban": true,
          "subway": true,
          "tram": true,
          "bus": true,
          "ferry": true,
          "express": true,
          "regional": true
        },
        "company": "VBB",
        "categories": [
          2
        ],
        "validFrom": "2022-04-26T15:00:00+02:00",
        "validUntil": "2022-04-26T18:00:00+02:00",
        "modified": "2022-04-26T16:57:16+02:00"
      },
      {
        "id": "144719",
        "type": "warning",
        "summary": "Masks are mandatory!",
        "text": "Please wear an FFP2 mask in the vehicles.\n<a href=\"https://www.vbb.de/corona\" target=\"_blank\" rel=\"noopener\">Further information (in German language)</a>",
        "icon": {
          "type": "HIM0",
          "title": null
        },
        "priority": 100,
        "products": {
          "suburban": true,
          "subway": true,
          "tram": true,
          "bus": true,
          "ferry": true,
          "express": true,
          "regional": true
        },
        "company": "VBB",
        "categories": [
          0
        ],
        "validFrom": "2021-11-24T00:00:00+01:00",
        "validUntil": "2022-12-31T00:00:00+01:00",
        "modified": "2022-04-01T06:48:49+02:00"
      }
    ],
    "origin": null,
    "destination": null,
    "currentTripPosition": {
      "type": "location",
      "latitude": 52.502874,
      "longitude": 13.470749
    }
  },
  {
    "tripId": "1|818|3|86|26042022",
    "stop": {
      "type": "stop",
      "id": "900000160004",
      "name": "S+U Lichtenberg",
      "location": {
        "type": "location",
        "id": "900160004",
        "latitude": 52.510676,
        "longitude": 13.498355
      },
      "products": {
        "suburban": true,
        "subway": true,
        "tram": true,
        "bus": true,
        "ferry": false,
        "express": true,
        "regional": true
      }
    },
    "when": "2022-04-26T17:50:00+02:00",
    "plannedWhen": "2022-04-26T17:50:00+02:00",
    "delay": 0,
    "platform": "22",
    "plannedPlatform": "22",
    "direction": null,
    "provenance": "Eberswalde, Hbf",
    "line": {
      "type": "line",
      "id": "rb24",
      "fahrtNr": "1052",
      "name": "RB24",
      "public": true,
      "adminCode": "800154",
      "productName": "RB",
      "mode": "train",
      "product": "regional",
      "operator": {
        "type": "operator",
        "id": "db-regio-ag",
        "name": "DB Regio AG"
      },
      "symbol": "RB",
      "nr": 24,
      "metro": false,
      "express": false,
      "night": false
    },
    "remarks": [
      {
        "type": "hint",
        "code": "FB",
        "text": "Bicycle conveyance"
      },
      {
        "type": "hint",
        "code": "PF",
        "text": "Please wear an FFP2 mask. You are legally required to do so"
      },
      {
        "type": "hint",
        "code": "kx",
        "text": "vehicle-mounted accessaid"
      },
      {
        "id": "162285",
        "type": "warning",
        "summary": "Information.",
        "text": "Bauvorankündigung: Am 30.04.22 und 01.05.22 kommt es auf der Linie RB24 zwischen Eberswalde Hbf und Berlin-Lichtenberg zu baubedingten Fahrplanänderungen mit Zugausfällen. Die geänderten Fahrpläne sind bereits in der Reiseauskunft abrufbar.\n<a href=\"https://bauinfos.deutschebahn.com/rf/rb24_3004-01052022_fahrplan1.pdf\" target=\"_blank\" rel=\"noopener\">weitere Information:</a>",
        "icon": {
          "type": "HIM0",
          "title": null
        },
        "priority": 50,
        "products": {
          "suburban": true,
          "subway": true,
          "tram": true,
          "bus": true,
          "ferry": true,
          "express": true,
          "regional": true
        },
        "company": "VBB",
        "categories": [
          0
        ],
        "validFrom": "2022-04-26T00:00:00+02:00",
        "validUntil": "2022-04-29T23:59:00+02:00",
        "modified": "2022-04-22T08:50:03+02:00"
      },
      {
        "id": "144719",
        "type": "warning",
        "summary": "Masks are mandatory!",
        "text": "Please wear an FFP2 mask in the vehicles.\n<a href=\"https://www.vbb.de/corona\" target=\"_blank\" rel=\"noopener\">Further information (in German language)</a>",
        "icon": {
          "type": "HIM0",
          "title": null
        },
        "priority": 100,
        "products": {
          "suburban": true,
          "subway": true,
          "tram": true,
          "bus": true,
          "ferry": true,
          "express": true,
          "regional": true
        },
        "company": "VBB",
        "categories": [
          0
        ],
        "validFrom": "2021-11-24T00:00:00+01:00",
        "validUntil": "2022-12-31T00:00:00+01:00",
        "modified": "2022-04-01T06:48:49+02:00"
      }
    ],
    "origin": null,
    "destination": null,
    "currentTripPosition": {
      "type": "location",
      "latitude": 52.516205,
      "longitude": 13.536074
    }
  },
  {
    "tripId": "1|36775|0|86|26042022",
    "stop": {
      "type": "stop",
      "id": "900000160701",
      "name": "S+U Lichtenberg [U5]",
      "location": {
        "type": "location",
        "id": "900160701",
        "latitude": 52.511135,
        "longitude": 13.498499
      },
      "products": {
        "suburban": true,
        "subway": true,
        "tram": true,
        "bus": true,
        "ferry": false,
        "express": true,
        "regional": true
      }
    },
    "when": "2022-04-26T17:50:00+02:00",
    "plannedWhen": "2022-04-26T17:50:00+02:00",
    "delay": 0,
    "platform": "1",
    "plannedPlatform": "1",
    "direction": null,
    "provenance": "U Hönow",
    "line": {
      "type": "line",
      "id": "u5",
      "fahrtNr": "16091",
      "name": "U5",
      "public": true,
      "adminCode": "BVU",
      "productName": "U",
      "mode": "train",
      "product": "subway",
      "operator": {
        "type": "operator",
        "id": "berliner-verkehrsbetriebe",
        "name": "Berliner Verkehrsbetriebe"
      },
      "symbol": "U",
      "nr": 5,
      "metro": false,
      "express": false,
      "night": false
    },
    "remarks": [
      {
        "type": "hint",
        "code": "bf",
        "text": "barrier-free"
      },
      {
        "type": "hint",
        "code": "FB",
        "text": "Bicycle conveyance"
      },
      {
        "id": "144719",
        "type": "warning",
        "summary": "Masks are mandatory!",
        "text": "Please wear an FFP2 mask in the vehicles.\n<a href=\"https://www.vbb.de/corona\" target=\"_blank\" rel=\"noopener\">Further information (in German language)</a>",
        "icon": {
          "type": "HIM0",
          "title": null
        },
        "priority": 100,
        "products": {
          "suburban": true,
          "subway": true,
          "tram": true,
          "bus": true,
          "ferry": true,
          "express": true,
          "regional": true
        },
        "company": "VBB",
        "categories": [
          0
        ],
        "validFrom": "2021-11-24T00:00:00+01:00",
        "validUntil": "2022-12-31T00:00:00+01:00",
        "modified": "2022-04-01T06:48:49+02:00"
      }
    ],
    "origin": null,
    "destination": null,
    "currentTripPosition": {
      "type": "location",
      "latitude": 52.503485,
      "longitude": 13.515902
    }
  },
  {
    "tripId": "1|36884|2|86|26042022",
    "stop": {
      "type": "stop",
      "id": "900000160701",
      "name": "S+U Lichtenberg [U5]",
      "location": {
        "type": "location",
        "id": "900160701",
        "latitude": 52.511135,
        "longitude": 13.498499
      },
      "products": {
        "suburban": true,
        "subway": true,
        "tram": true,
        "bus": true,
        "ferry": false,
        "express": true,
        "regional": true
      }
    },
    "when": "2022-04-26T17:50:00+02:00",
    "plannedWhen": "2022-04-26T17:50:00+02:00",
    "delay": 0,
    "platform": "2",
    "plannedPlatform": "2",
    "direction": null,
    "provenance": "S+U Berlin Hauptbahnhof",
    "line": {
      "type": "line",
      "id": "u5",
      "fahrtNr": "15476",
      "name": "U5",
      "public": true,
      "adminCode": "BVU",
      "productName": "U",
      "mode": "train",
      "product": "subway",
      "operator": {
        "type": "operator",
        "id": "berliner-verkehrsbetriebe",
        "name": "Berliner Verkehrsbetriebe"
      },
      "symbol": "U",
      "nr": 5,
      "metro": false,
      "express": false,
      "night": false
    },
    "remarks": [
      {
        "type": "hint",
        "code": "bf",
        "text": "barrier-free"
      },
      {
        "type": "hint",
        "code": "FB",
        "text": "Bicycle conveyance"
      },
      {
        "id": "144719",
        "type": "warning",
        "summary": "Masks are mandatory!",
        "text": "Please wear an FFP2 mask in the vehicles.\n<a href=\"https://www.vbb.de/corona\" target=\"_blank\" rel=\"noopener\">Further information (in German language)</a>",
        "icon": {
          "type": "HIM0",
          "title": null
        },
        "priority": 100,
        "products": {
          "suburban": true,
          "subway": true,
          "tram": true,
          "bus": true,
          "ferry": true,
          "express": true,
          "regional": true
        },
        "company": "VBB",
        "categories": [
          0
        ],
        "validFrom": "2021-11-24T00:00:00+01:00",
        "validUntil": "2022-12-31T00:00:00+01:00",
        "modified": "2022-04-01T06:48:49+02:00"
      }
    ],
    "origin": null,
    "destination": null,
    "currentTripPosition": {
      "type": "location",
      "latitude": 52.513589,
      "longitude": 13.47599
    }
  },
  {
    "tripId": "1|40982|42|86|26042022",
    "stop": {
      "type": "stop",
      "id": "900000160004",
      "name": "S+U Lichtenberg",
      "location": {
        "type": "location",
        "id": "900160004",
        "latitude": 52.510676,
        "longitude": 13.498355
      },
      "products": {
        "suburban": true,
        "subway": true,
        "tram": true,
        "bus": true,
        "ferry": false,
        "express": true,
        "regional": true
      }
    },
    "when": "2022-04-26T17:51:00+02:00",
    "plannedWhen": "2022-04-26T17:51:00+02:00",
    "delay": 0,
    "platform": "2",
    "plannedPlatform": "2",
    "direction": null,
    "provenance": "S Wartenberg",
    "line": {
      "type": "line",
      "id": "s75",
      "fahrtNr": "20764",
      "name": "S75",
      "public": true,
      "adminCode": "DBS",
      "productName": "S",
      "mode": "train",
      "product": "suburban",
      "operator": {
        "type": "operator",
        "id": "s-bahn-berlin-gmbh",
        "name": "S-Bahn Berlin GmbH"
      },
      "symbol": "S",
      "nr": 75,
      "metro": false,
      "express": false,
      "night": false
    },
    "remarks": [
      {
        "type": "hint",
        "code": "bf",
        "text": "barrier-free"
      },
      {
        "type": "hint",
        "code": "FB",
        "text": "Bicycle conveyance"
      },
      {
        "id": "144719",
        "type": "warning",
        "summary": "Masks are mandatory!",
        "text": "Please wear an FFP2 mask in the vehicles.\n<a href=\"https://www.vbb.de/corona\" target=\"_blank\" rel=\"noopener\">Further information (in German language)</a>",
        "icon": {
          "type": "HIM0",
          "title": null
        },
        "priority": 100,
        "products": {
          "suburban": true,
          "subway": true,
          "tram": true,
          "bus": true,
          "ferry": true,
          "express": true,
          "regional": true
        },
        "company": "VBB",
        "categories": [
          0
        ],
        "validFrom": "2021-11-24T00:00:00+01:00",
        "validUntil": "2022-12-31T00:00:00+01:00",
        "modified": "2022-04-01T06:48:49+02:00"
      }
    ],
    "origin": null,
    "destination": null,
    "currentTripPosition": {
      "type": "location",
      "latitude": 52.514074,
      "longitude": 13.531534
    }
  },
  {
    "tripId": "1|7634|8|86|26042022",
    "stop": {
      "type": "stop",
      "id": "900000160702",
      "name": "S+U Lichtenberg [Bus]",
      "location": {
        "type": "location",
        "id": "900160702",
        "latitude": 52.510389,
        "longitude": 13.49947
      },
      "products": {
        "suburban": true,
        "subway": true,
        "tram": true,
        "bus": true,
        "ferry": false,
        "express": true,
        "regional": true
      }
    },
    "when": "2022-04-26T17:52:00+02:00",
    "plannedWhen": "2022-04-26T17:48:00+02:00",
    "delay": 240,
    "platform": null,
    "plannedPlatform": null,
    "direction": null,
    "provenance": "Waldesruh, Mahlsdorfer Allee",
    "line": {
      "type": "line",
      "id": "108",
      "fahrtNr": "21240",
      "name": "108",
      "public": true,
      "adminCode": "BVB",
      "productName": "Bus",
      "mode": "bus",
      "product": "bus",
      "operator": {
        "type": "operator",
        "id": "berliner-verkehrsbetriebe",
        "name": "Berliner Verkehrsbetriebe"
      },
      "symbol": null,
      "nr": 108,
      "metro": false,
      "express": false,
      "night": false
    },
    "remarks": [
      {
        "type": "hint",
        "code": "bf",
        "text": "barrier-free"
      },
      {
        "id": "144719",
        "type": "warning",
        "summary": "Masks are mandatory!",
        "text": "Please wear an FFP2 mask in the vehicles.\n<a href=\"https://www.vbb.de/corona\" target=\"_blank\" rel=\"noopener\">Further information (in German language)</a>",
        "icon": {
          "type": "HIM0",
          "title": null
        },
        "priority": 100,
        "products": {
          "suburban": true,
          "subway": true,
          "tram": true,
          "bus": true,
          "ferry": true,
          "express": true,
          "regional": true
        },
        "company": "VBB",
        "categories": [
          0
        ],
        "validFrom": "2021-11-24T00:00:00+01:00",
        "validUntil": "2022-12-31T00:00:00+01:00",
        "modified": "2022-04-01T06:48:49+02:00"
      }
    ],
    "origin": null,
    "destination": null,
    "currentTripPosition": {
      "type": "location",
      "latitude": 52.509822,
      "longitude": 13.519381
    }
  },
  {
    "tripId": "1|40718|16|86|26042022",
    "stop": {
      "type": "stop",
      "id": "900000160004",
      "name": "S+U Lichtenberg",
      "location": {
        "type": "location",
        "id": "900160004",
        "latitude": 52.510676,
        "longitude": 13.498355
      },
      "products": {
        "suburban": true,
        "subway": true,
        "tram": true,
        "bus": true,
        "ferry": false,
        "express": true,
        "regional": true
      }
    },
    "when": "2022-04-26T17:52:00+02:00",
    "plannedWhen": "2022-04-26T17:50:00+02:00",
    "delay": 120,
    "platform": "1",
    "plannedPlatform": "1",
    "direction": null,
    "provenance": "S Westkreuz",
    "line": {
      "type": "line",
      "id": "s5",
      "fahrtNr": "19636",
      "name": "S5",
      "public": true,
      "adminCode": "DBS",
      "productName": "S",
      "mode": "train",
      "product": "suburban",
      "operator": {
        "type": "operator",
        "id": "s-bahn-berlin-gmbh",
        "name": "S-Bahn Berlin GmbH"
      },
      "symbol": "S",
      "nr": 5,
      "metro": false,
      "express": false,
      "night": false
    },
    "remarks": [
      {
        "type": "hint",
        "code": "bf",
        "text": "barrier-free"
      },
      {
        "type": "hint",
        "code": "FB",
        "text": "Bicycle conveyance"
      },
      {
        "id": "144719",
        "type": "warning",
        "summary": "Masks are mandatory!",
        "text": "Please wear an FFP2 mask in the vehicles.\n<a href=\"https://www.vbb.de/corona\" target=\"_blank\" rel=\"noopener\">Further information (in German language)</a>",
        "icon": {
          "type": "HIM0",
          "title": null
        },
        "priority": 100,
        "products": {
          "suburban": true,
          "subway": true,
          "tram": true,
          "bus": true,
          "ferry": true,
          "express": true,
          "regional": true
        },
        "company": "VBB",
        "categories": [
          0
        ],
        "validFrom": "2021-11-24T00:00:00+01:00",
        "validUntil": "2022-12-31T00:00:00+01:00",
        "modified": "2022-04-01T06:48:49+02:00"
      }
    ],
    "origin": null,
    "destination": null,
    "currentTripPosition": {
      "type": "location",
      "latitude": 52.505588,
      "longitude": 13.454056
    }
  },
  {
    "tripId": "1|40997|40|86|26042022",
    "stop": {
      "type": "stop",
      "id": "900000160004",
      "name": "S+U Lichtenberg",
      "location": {
        "type": "location",
        "id": "900160004",
        "latitude": 52.510676,
        "longitude": 13.498355
      },
      "products": {
        "suburban": true,
        "subway": true,
        "tram": true,
        "bus": true,
        "ferry": false,
        "express": true,
        "regional": true
      }
    },
    "when": "2022-04-26T17:53:00+02:00",
    "plannedWhen": "2022-04-26T17:53:00+02:00",
    "delay": 0,
    "platform": "1",
    "plannedPlatform": "1",
    "direction": null,
    "provenance": "S+U Warschauer Str.",
    "line": {
      "type": "line",
      "id": "s75",
      "fahrtNr": "20676",
      "name": "S75",
      "public": true,
      "adminCode": "DBS",
      "productName": "S",
      "mode": "train",
      "product": "suburban",
      "operator": {
        "type": "operator",
        "id": "s-bahn-berlin-gmbh",
        "name": "S-Bahn Berlin GmbH"
      },
      "symbol": "S",
      "nr": 75,
      "metro": false,
      "express": false,
      "night": false
    },
    "remarks": [
      {
        "type": "hint",
        "code": "bf",
        "text": "barrier-free"
      },
      {
        "type": "hint",
        "code": "FB",
        "text": "Bicycle conveyance"
      },
      {
        "id": "144719",
        "type": "warning",
        "summary": "Masks are mandatory!",
        "text": "Please wear an FFP2 mask in the vehicles.\n<a href=\"https://www.vbb.de/corona\" target=\"_blank\" rel=\"noopener\">Further information (in German language)</a>",
        "icon": {
          "type": "HIM0",
          "title": null
        },
        "priority": 100,
        "products": {
          "suburban": true,
          "subway": true,
          "tram": true,
          "bus": true,
          "ferry": true,
          "express": true,
          "regional": true
        },
        "company": "VBB",
        "categories": [
          0
        ],
        "validFrom": "2021-11-24T00:00:00+01:00",
        "validUntil": "2022-12-31T00:00:00+01:00",
        "modified": "2022-04-01T06:48:49+02:00"
      }
    ],
    "origin": null,
    "destination": null
  },
  {
    "tripId": "1|20192|14|86|26042022",
    "stop": {
      "type": "stop",
      "id": "900000160702",
      "name": "S+U Lichtenberg [Bus]",
      "location": {
        "type": "location",
        "id": "900160702",
        "latitude": 52.510389,
        "longitude": 13.49947
      },
      "products": {
        "suburban": true,
        "subway": true,
        "tram": true,
        "bus": true,
        "ferry": false,
        "express": true,
        "regional": true
      }
    },
    "when": "2022-04-26T17:55:00+02:00",
    "plannedWhen": "2022-04-26T17:55:00+02:00",
    "delay": 0,
    "platform": null,
    "plannedPlatform": null,
    "direction": null,
    "provenance": "S Karlshorst",
    "line": {
      "type": "line",
      "id": "296",
      "fahrtNr": "38766",
      "name": "296",
      "public": true,
      "adminCode": "BVB",
      "productName": "Bus",
      "mode": "bus",
      "product": "bus",
      "operator": {
        "type": "operator",
        "id": "berliner-verkehrsbetriebe",
        "name": "Berliner Verkehrsbetriebe"
      },
      "symbol": null,
      "nr": 296,
      "metro": false,
      "express": false,
      "night": false
    },
    "remarks": [
      {
        "type": "hint",
        "code": "bf",
        "text": "barrier-free"
      },
      {
        "id": "144719",
        "type": "warning",
        "summary": "Masks are mandatory!",
        "text": "Please wear an FFP2 mask in the vehicles.\n<a href=\"https://www.vbb.de/corona\" target=\"_blank\" rel=\"noopener\">Further information (in German language)</a>",
        "icon": {
          "type": "HIM0",
          "title": null
        },
        "priority": 100,
        "products": {
          "suburban": true,
          "subway": true,
          "tram": true,
          "bus": true,
          "ferry": true,
          "express": true,
          "regional": true
        },
        "company": "VBB",
        "categories": [
          0
        ],
        "validFrom": "2021-11-24T00:00:00+01:00",
        "validUntil": "2022-12-31T00:00:00+01:00",
        "modified": "2022-04-01T06:48:49+02:00"
      }
    ],
    "origin": null,
    "destination": null,
    "currentTripPosition": {
      "type": "location",
      "latitude": 52.499116,
      "longitude": 13.508054
    }
  },
  {
    "tripId": "1|36882|12|86|26042022",
    "stop": {
      "type": "stop",
      "id": "900000160701",
      "name": "S+U Lichtenberg [U5]",
      "location": {
        "type": "location",
        "id": "900160701",
        "latitude": 52.511135,
        "longitude": 13.498499
      },
      "products": {
        "suburban": true,
        "subway": true,
        "tram": true,
        "bus": true,
        "ferry": false,
        "express": true,
        "regional": true
      }
    },
    "when": "2022-04-26T17:55:00+02:00",
    "plannedWhen": "2022-04-26T17:55:00+02:00",
    "delay": 0,
    "platform": "2",
    "plannedPlatform": "2",
    "direction": null,
    "provenance": "S+U Berlin Hauptbahnhof",
    "line": {
      "type": "line",
      "id": "u5",
      "fahrtNr": "15477",
      "name": "U5",
      "public": true,
      "adminCode": "BVU",
      "productName": "U",
      "mode": "train",
      "product": "subway",
      "operator": {
        "type": "operator",
        "id": "berliner-verkehrsbetriebe",
        "name": "Berliner Verkehrsbetriebe"
      },
      "symbol": "U",
      "nr": 5,
      "metro": false,
      "express": false,
      "night": false
    },
    "remarks": [
      {
        "type": "hint",
        "code": "bf",
        "text": "barrier-free"
      },
      {
        "type": "hint",
        "code": "FB",
        "text": "Bicycle conveyance"
      },
      {
        "id": "144719",
        "type": "warning",
        "summary": "Masks are mandatory!",
        "text": "Please wear an FFP2 mask in the vehicles.\n<a href=\"https://www.vbb.de/corona\" target=\"_blank\" rel=\"noopener\">Further information (in German language)</a>",
        "icon": {
          "type": "HIM0",
          "title": null
        },
        "priority": 100,
        "products": {
          "suburban": true,
          "subway": true,
          "tram": true,
          "bus": true,
          "ferry": true,
          "express": true,
          "regional": true
        },
        "company": "VBB",
        "categories": [
          0
        ],
        "validFrom": "2021-11-24T00:00:00+01:00",
        "validUntil": "2022-12-31T00:00:00+01:00",
        "modified": "2022-04-01T06:48:49+02:00"
      }
    ],
    "origin": null,
    "destination": null,
    "currentTripPosition": {
      "type": "location",
      "latitude": 52.517148,
      "longitude": 13.440752
    }
  },
  {
    "tripId": "1|65607|4|86|26042022",
    "stop": {
      "type": "stop",
      "id": "900000160020",
      "name": "S+U Lichtenberg/Siegfriedstr.",
      "location": {
        "type": "location",
        "id": "900160020",
        "latitude": 52.511953,
        "longitude": 13.497654
      },
      "products": {
        "suburban": true,
        "subway": true,
        "tram": true,
        "bus": true,
        "ferry": false,
        "express": true,
        "regional": true
      }
    },
    "when": "2022-04-26T17:55:00+02:00",
    "plannedWhen": "2022-04-26T17:57:00+02:00",
    "delay": -120,
    "platform": null,
    "plannedPlatform": null,
    "direction": null,
    "provenance": "Falkenberg",
    "line": {
      "type": "line",
      "id": "256",
      "fahrtNr": "36273",
      "name": "256",
      "public": true,
      "adminCode": "BVB",
      "productName": "Bus",
      "mode": "bus",
      "product": "bus",
      "operator": {
        "type": "operator",
        "id": "berliner-verkehrsbetriebe",
        "name": "Berliner Verkehrsbetriebe"
      },
      "symbol": null,
      "nr": 256,
      "metro": false,
      "express": false,
      "night": false
    },
    "remarks": [
      {
        "type": "hint",
        "code": "bf",
        "text": "barrier-free"
      },
      {
        "id": "144719",
        "type": "warning",
        "summary": "Masks are mandatory!",
        "text": "Please wear an FFP2 mask in the vehicles.\n<a href=\"https://www.vbb.de/corona\" target=\"_blank\" rel=\"noopener\">Further information (in German language)</a>",
        "icon": {
          "type": "HIM0",
          "title": null
        },
        "priority": 100,
        "products": {
          "suburban": true,
          "subway": true,
          "tram": true,
          "bus": true,
          "ferry": true,
          "express": true,
          "regional": true
        },
        "company": "VBB",
        "categories": [
          0
        ],
        "validFrom": "2021-11-24T00:00:00+01:00",
        "validUntil": "2022-12-31T00:00:00+01:00",
        "modified": "2022-04-01T06:48:49+02:00"
      }
    ],
    "origin": null,
    "destination": null,
    "currentTripPosition": {
      "type": "location",
      "latitude": 52.532367,
      "longitude": 13.499955
    }
  },
  {
    "tripId": "1|36771|11|86|26042022",
    "stop": {
      "type": "stop",
      "id": "900000160701",
      "name": "S+U Lichtenberg [U5]",
      "location": {
        "type": "location",
        "id": "900160701",
        "latitude": 52.511135,
        "longitude": 13.498499
      },
      "products": {
        "suburban": true,
        "subway": true,
        "tram": true,
        "bus": true,
        "ferry": false,
        "express": true,
        "regional": true
      }
    },
    "when": "2022-04-26T17:56:00+02:00",
    "plannedWhen": "2022-04-26T17:55:00+02:00",
    "delay": 60,
    "platform": "1",
    "plannedPlatform": "1",
    "direction": null,
    "provenance": "U Hönow",
    "line": {
      "type": "line",
      "id": "u5",
      "fahrtNr": "16092",
      "name": "U5",
      "public": true,
      "adminCode": "BVU",
      "productName": "U",
      "mode": "train",
      "product": "subway",
      "operator": {
        "type": "operator",
        "id": "berliner-verkehrsbetriebe",
        "name": "Berliner Verkehrsbetriebe"
      },
      "symbol": "U",
      "nr": 5,
      "metro": false,
      "express": false,
      "night": false
    },
    "remarks": [
      {
        "type": "hint",
        "code": "bf",
        "text": "barrier-free"
      },
      {
        "type": "hint",
        "code": "FB",
        "text": "Bicycle conveyance"
      },
      {
        "id": "144719",
        "type": "warning",
        "summary": "Masks are mandatory!",
        "text": "Please wear an FFP2 mask in the vehicles.\n<a href=\"https://www.vbb.de/corona\" target=\"_blank\" rel=\"noopener\">Further information (in German language)</a>",
        "icon": {
          "type": "HIM0",
          "title": null
        },
        "priority": 100,
        "products": {
          "suburban": true,
          "subway": true,
          "tram": true,
          "bus": true,
          "ferry": true,
          "express": true,
          "regional": true
        },
        "company": "VBB",
        "categories": [
          0
        ],
        "validFrom": "2021-11-24T00:00:00+01:00",
        "validUntil": "2022-12-31T00:00:00+01:00",
        "modified": "2022-04-01T06:48:49+02:00"
      }
    ],
    "origin": null,
    "destination": null,
    "currentTripPosition": {
      "type": "location",
      "latitude": 52.50824,
      "longitude": 13.564758
    }
  },
  {
    "tripId": "1|18655|0|86|26042022",
    "stop": {
      "type": "stop",
      "id": "900000160020",
      "name": "S+U Lichtenberg/Siegfriedstr.",
      "location": {
        "type": "location",
        "id": "900160020",
        "latitude": 52.511953,
        "longitude": 13.497654
      },
      "products": {
        "suburban": true,
        "subway": true,
        "tram": true,
        "bus": true,
        "ferry": false,
        "express": true,
        "regional": true
      }
    },
    "when": "2022-04-26T17:56:00+02:00",
    "plannedWhen": "2022-04-26T17:56:00+02:00",
    "delay": 0,
    "platform": null,
    "plannedPlatform": null,
    "direction": null,
    "provenance": "Zentralfriedhof",
    "line": {
      "type": "line",
      "id": "256",
      "fahrtNr": "36307",
      "name": "256",
      "public": true,
      "adminCode": "BVB",
      "productName": "Bus",
      "mode": "bus",
      "product": "bus",
      "operator": {
        "type": "operator",
        "id": "berliner-verkehrsbetriebe",
        "name": "Berliner Verkehrsbetriebe"
      },
      "symbol": null,
      "nr": 256,
      "metro": false,
      "express": false,
      "night": false
    },
    "remarks": [
      {
        "type": "hint",
        "code": "bf",
        "text": "barrier-free"
      },
      {
        "id": "144719",
        "type": "warning",
        "summary": "Masks are mandatory!",
        "text": "Please wear an FFP2 mask in the vehicles.\n<a href=\"https://www.vbb.de/corona\" target=\"_blank\" rel=\"noopener\">Further information (in German language)</a>",
        "icon": {
          "type": "HIM0",
          "title": null
        },
        "priority": 100,
        "products": {
          "suburban": true,
          "subway": true,
          "tram": true,
          "bus": true,
          "ferry": true,
          "express": true,
          "regional": true
        },
        "company": "VBB",
        "categories": [
          0
        ],
        "validFrom": "2021-11-24T00:00:00+01:00",
        "validUntil": "2022-12-31T00:00:00+01:00",
        "modified": "2022-04-01T06:48:49+02:00"
      }
    ],
    "origin": null,
    "destination": null
  },
  {
    "tripId": "1|40828|53|86|26042022",
    "stop": {
      "type": "stop",
      "id": "900000160004",
      "name": "S+U Lichtenberg",
      "location": {
        "type": "location",
        "id": "900160004",
        "latitude": 52.510676,
        "longitude": 13.498355
      },
      "products": {
        "suburban": true,
        "subway": true,
        "tram": true,
        "bus": true,
        "ferry": false,
        "express": true,
        "regional": true
      }
    },
    "when": "2022-04-26T17:56:00+02:00",
    "plannedWhen": "2022-04-26T17:56:00+02:00",
    "delay": 0,
    "platform": "2",
    "plannedPlatform": "2",
    "direction": null,
    "provenance": "S Ahrensfelde",
    "line": {
      "type": "line",
      "id": "s7",
      "fahrtNr": "20518",
      "name": "S7",
      "public": true,
      "adminCode": "DBS",
      "productName": "S",
      "mode": "train",
      "product": "suburban",
      "operator": {
        "type": "operator",
        "id": "s-bahn-berlin-gmbh",
        "name": "S-Bahn Berlin GmbH"
      },
      "symbol": "S",
      "nr": 7,
      "metro": false,
      "express": false,
      "night": false
    },
    "remarks": [
      {
        "type": "hint",
        "code": "bf",
        "text": "barrier-free"
      },
      {
        "type": "hint",
        "code": "FB",
        "text": "Bicycle conveyance"
      },
      {
        "id": "163085",
        "type": "warning",
        "summary": "Störung.",
        "text": "Nach einem Polizeieinsatz (Personen im Gleis) im Bereich Warschauer Str. ist noch mit Verspätungen und vereinzelten Zugausfällen zu rechnen.",
        "icon": {
          "type": "HIM2",
          "title": null
        },
        "priority": 50,
        "products": {
          "suburban": true,
          "subway": true,
          "tram": true,
          "bus": true,
          "ferry": true,
          "express": true,
          "regional": true
        },
        "company": "VBB",
        "categories": [
          2
        ],
        "validFrom": "2022-04-26T15:00:00+02:00",
        "validUntil": "2022-04-26T18:00:00+02:00",
        "modified": "2022-04-26T16:57:16+02:00"
      },
      {
        "id": "144719",
        "type": "warning",
        "summary": "Masks are mandatory!",
        "text": "Please wear an FFP2 mask in the vehicles.\n<a href=\"https://www.vbb.de/corona\" target=\"_blank\" rel=\"noopener\">Further information (in German language)</a>",
        "icon": {
          "type": "HIM0",
          "title": null
        },
        "priority": 100,
        "products": {
          "suburban": true,
          "subway": true,
          "tram": true,
          "bus": true,
          "ferry": true,
          "express": true,
          "regional": true
        },
        "company": "VBB",
        "categories": [
          0
        ],
        "validFrom": "2021-11-24T00:00:00+01:00",
        "validUntil": "2022-12-31T00:00:00+01:00",
        "modified": "2022-04-01T06:48:49+02:00"
      }
    ],
    "origin": null,
    "destination": null,
    "currentTripPosition": {
      "type": "location",
      "latitude": 52.541338,
      "longitude": 13.539283
    }
  },
  {
    "tripId": "1|77162|0|86|26042022",
    "stop": {
      "type": "stop",
      "id": "900000160004",
      "name": "S+U Lichtenberg",
      "location": {
        "type": "location",
        "id": "900160004",
        "latitude": 52.510676,
        "longitude": 13.498355
      },
      "products": {
        "suburban": true,
        "subway": true,
        "tram": true,
        "bus": true,
        "ferry": false,
        "express": true,
        "regional": true
      }
    },
    "when": "2022-04-26T17:57:00+02:00",
    "plannedWhen": "2022-04-26T17:57:00+02:00",
    "delay": 0,
    "platform": "17",
    "plannedPlatform": "17",
    "direction": null,
    "provenance": "Templin, Stadt",
    "line": {
      "type": "line",
      "id": "rb12",
      "fahrtNr": "1366",
      "name": "RB12",
      "public": true,
      "adminCode": "NEB",
      "productName": "RB",
      "mode": "train",
      "product": "regional",
      "operator": {
        "type": "operator",
        "id": "neb-betriebsgesellschaft-mbh",
        "name": "NEB Betriebsgesellschaft mbH"
      },
      "symbol": "RB",
      "nr": 12,
      "metro": false,
      "express": false,
      "night": false
    },
    "remarks": [
      {
        "type": "hint",
        "code": "bf",
        "text": "barrier-free"
      },
      {
        "type": "hint",
        "code": "FB",
        "text": "Bicycle conveyance"
      },
      {
        "id": "144719",
        "type": "warning",
        "summary": "Masks are mandatory!",
        "text": "Please wear an FFP2 mask in the vehicles.\n<a href=\"https://www.vbb.de/corona\" target=\"_blank\" rel=\"noopener\">Further information (in German language)</a>",
        "icon": {
          "type": "HIM0",
          "title": null
        },
        "priority": 100,
        "products": {
          "suburban": true,
          "subway": true,
          "tram": true,
          "bus": true,
          "ferry": true,
          "express": true,
          "regional": true
        },
        "company": "VBB",
        "categories": [
          0
        ],
        "validFrom": "2021-11-24T00:00:00+01:00",
        "validUntil": "2022-12-31T00:00:00+01:00",
        "modified": "2022-04-01T06:48:49+02:00"
      }
    ],
    "origin": null,
    "destination": null,
    "currentTripPosition": {
      "type": "location",
      "latitude": 52.582698,
      "longitude": 13.491137
    }
  },
  {
    "tripId": "1|40542|2|86|26042022",
    "stop": {
      "type": "stop",
      "id": "900000160004",
      "name": "S+U Lichtenberg",
      "location": {
        "type": "location",
        "id": "900160004",
        "latitude": 52.510676,
        "longitude": 13.498355
      },
      "products": {
        "suburban": true,
        "subway": true,
        "tram": true,
        "bus": true,
        "ferry": false,
        "express": true,
        "regional": true
      }
    },
    "when": "2022-04-26T17:58:00+02:00",
    "plannedWhen": "2022-04-26T17:53:00+02:00",
    "delay": 300,
    "platform": "2",
    "plannedPlatform": "2",
    "direction": null,
    "provenance": "S Strausberg Nord",
    "line": {
      "type": "line",
      "id": "s5",
      "fahrtNr": "19460",
      "name": "S5",
      "public": true,
      "adminCode": "DBS",
      "productName": "S",
      "mode": "train",
      "product": "suburban",
      "operator": {
        "type": "operator",
        "id": "s-bahn-berlin-gmbh",
        "name": "S-Bahn Berlin GmbH"
      },
      "symbol": "S",
      "nr": 5,
      "metro": false,
      "express": false,
      "night": false
    },
    "remarks": [
      {
        "type": "hint",
        "code": "bf",
        "text": "barrier-free"
      },
      {
        "type": "hint",
        "code": "FB",
        "text": "Bicycle conveyance"
      },
      {
        "id": "163090",
        "type": "warning",
        "summary": "Störung.",
        "text": "Nach einem beendeten Polizeieinsatz Warschauer Str. und Westkreuz verkehren die Züge der S5 noch unregelmäßig . Die zusätzlichen Züge zwischen Mahlsdorf und Ostbahnhof verkehren nicht.",
        "icon": {
          "type": "HIM2",
          "title": null
        },
        "priority": 50,
        "products": {
          "suburban": true,
          "subway": true,
          "tram": true,
          "bus": true,
          "ferry": true,
          "express": true,
          "regional": true
        },
        "company": "VBB",
        "categories": [
          2
        ],
        "validFrom": "2022-04-26T15:00:00+02:00",
        "validUntil": "2022-04-26T23:59:00+02:00",
        "modified": "2022-04-26T16:55:48+02:00"
      },
      {
        "id": "144719",
        "type": "warning",
        "summary": "Masks are mandatory!",
        "text": "Please wear an FFP2 mask in the vehicles.\n<a href=\"https://www.vbb.de/corona\" target=\"_blank\" rel=\"noopener\">Further information (in German language)</a>",
        "icon": {
          "type": "HIM0",
          "title": null
        },
        "priority": 100,
        "products": {
          "suburban": true,
          "subway": true,
          "tram": true,
          "bus": true,
          "ferry": true,
          "express": true,
          "regional": true
        },
        "company": "VBB",
        "categories": [
          0
        ],
        "validFrom": "2021-11-24T00:00:00+01:00",
        "validUntil": "2022-12-31T00:00:00+01:00",
        "modified": "2022-04-01T06:48:49+02:00"
      }
    ],
    "origin": null,
    "destination": null,
    "currentTripPosition": {
      "type": "location",
      "latitude": 52.511971,
      "longitude": 13.594009
    }
  }
]
