{
  "data": [
    {
      "type": "vehicle",
      "id": "eadb78f8-ed98-4415-ba40-8b3c2a4823bf",
      "attributes": {
        "state": "ACTIVE",
        "lastLocationUpdate": "2022-06-27T16:59:55Z",
        "lastStateChange": "2022-06-23T07:09:31Z",
        "batteryLevel": 60,
        "currentRangeMeters": 25000,
        "lat": 52.507862,
        "lng": 13.498956,
        "maxSpeed": 20,
        "zoneId": "BERLIN",
        "code": 173668,
        "iotVendor": "okai",
        "licencePlate": "682YFY",
        "isRentable": true,
        "vehicleType": "escooter",
        "hasHelmetBox": false,
        "hasHelmet": false
      }
    },
    {
      "type": "vehicle",
      "id": "831debe5-fbbb-49ac-af69-7ccd155304e2",
      "attributes": {
        "state": "ACTIVE",
        "lastLocationUpdate": "2022-06-27T16:56:47Z",
        "lastStateChange": "2022-06-25T18:58:25Z",
        "batteryLevel": 80,
        "currentRangeMeters": 35000,
        "lat": 52.507675,
        "lng": 13.497509,
        "maxSpeed": 20,
        "zoneId": "BERLIN",
        "code": 176077,
        "iotVendor": "okai",
        "licencePlate": "696YGE",
        "isRentable": true,
        "vehicleType": "escooter",
        "hasHelmetBox": false,
        "hasHelmet": false
      }
    },
    {
      "type": "vehicle",
      "id": "09dfdbda-76d1-4bf1-880c-4d27203e59e9",
      "attributes": {
        "state": "ACTIVE",
        "lastLocationUpdate": "2022-06-27T17:02:04Z",
        "lastStateChange": "2022-06-26T22:15:17Z",
        "batteryLevel": 100,
        "currentRangeMeters": 46000,
        "lat": 52.511211,
        "lng": 13.497221,
        "maxSpeed": 20,
        "zoneId": "BERLIN",
        "code": 196295,
        "iotVendor": "okai",
        "licencePlate": "547YGI",
        "isRentable": true,
        "vehicleType": "escooter",
        "hasHelmetBox": false,
        "hasHelmet": false
      }
    },
    {
      "type": "vehicle",
      "id": "69bc374c-1341-4526-9b36-6ab4bd1055dc",
      "attributes": {
        "state": "ACTIVE",
        "lastLocationUpdate": "2022-06-27T16:53:26Z",
        "lastStateChange": "2022-06-23T22:11:00Z",
        "batteryLevel": 72,
        "currentRangeMeters": 31000,
        "lat": 52.508569,
        "lng": 13.499092,
        "maxSpeed": 20,
        "zoneId": "BERLIN",
        "code": 200586,
        "iotVendor": "okai",
        "licencePlate": "827YGH",
        "isRentable": true,
        "vehicleType": "escooter",
        "hasHelmetBox": false,
        "hasHelmet": false
      }
    },
    {
      "type": "vehicle",
      "id": "f6815c39-403d-4a57-9b3b-e8fb132fe364",
      "attributes": {
        "state": "ACTIVE",
        "lastLocationUpdate": "2022-06-27T17:02:59Z",
        "lastStateChange": "2022-06-23T10:02:16Z",
        "batteryLevel": 52,
        "currentRangeMeters": 20000,
        "lat": 52.507782,
        "lng": 13.497512,
        "maxSpeed": 20,
        "zoneId": "BERLIN",
        "code": 289743,
        "iotVendor": "okai",
        "licencePlate": "673YFL",
        "isRentable": true,
        "vehicleType": "escooter",
        "hasHelmetBox": false,
        "hasHelmet": false
      }
    }
  ]
}
