{
  "data": [
    {
      "type": "vehicle",
      "id": "285de2c5-bf61-498a-8b20-2cde711fa0b8",
      "attributes": {
        "state": "ACTIVE",
        "lastLocationUpdate": "2023-01-29T09:34:18Z",
        "lastStateChange": "2023-01-25T08:33:46Z",
        "batteryLevel": 46,
        "currentRangeMeters": 17000,
        "lat": 52.509541,
        "lng": 13.498076,
        "maxSpeed": 20,
        "zoneId": "BERLIN",
        "code": 192586,
        "iotVendor": "okai",
        "licencePlate": "669YGL",
        "isRentable": true,
        "vehicleType": "escooter",
        "hasHelmetBox": false,
        "hasHelmet": false
      }
    },
    {
      "type": "vehicle",
      "id": "5144a729-3296-4e2e-bf88-74ee5e1d4d81",
      "attributes": {
        "state": "ACTIVE",
        "lastLocationUpdate": "2023-01-29T09:36:49Z",
        "lastStateChange": "2023-01-27T09:54:51Z",
        "batteryLevel": 55,
        "currentRangeMeters": 22000,
        "lat": 52.510284,
        "lng": 13.49932,
        "maxSpeed": 20,
        "zoneId": "BERLIN",
        "code": 212379,
        "iotVendor": "okai",
        "licencePlate": "294YFN",
        "isRentable": true,
        "vehicleType": "escooter",
        "hasHelmetBox": false,
        "hasHelmet": false
      }
    }
  ]
}
