{
  "data": [
    {
      "type": "vehicle",
      "id": "e4c7b8d2-e28c-4ce5-8cf3-c34f9b425818",
      "attributes": {
        "state": "ACTIVE",
        "lastLocationUpdate": "2023-10-07T15:07:38Z",
        "lastStateChange": "2023-09-29T10:11:51Z",
        "batteryLevel": 57,
        "currentRangeMeters": 23000,
        "lat": 52.511207,
        "lng": 13.497161,
        "maxSpeed": 20,
        "zoneId": "BERLIN",
        "code": 200928,
        "iotVendor": "okai",
        "licencePlate": "314WNX",
        "isRentable": true,
        "vehicleType": "escooter",
        "hasHelmetBox": false,
        "hasHelmet": false
      }
    },
    {
      "type": "vehicle",
      "id": "a8802e50-f774-450f-b687-8e602d2a89c4",
      "attributes": {
        "state": "ACTIVE",
        "lastLocationUpdate": "2023-10-07T15:35:18Z",
        "lastStateChange": "2023-10-05T07:11:49Z",
        "batteryLevel": 91,
        "currentRangeMeters": 41000,
        "lat": 52.508953,
        "lng": 13.497703,
        "maxSpeed": 20,
        "zoneId": "BERLIN",
        "code": 201100,
        "iotVendor": "okai",
        "licencePlate": "799WPM",
        "isRentable": true,
        "vehicleType": "escooter",
        "hasHelmetBox": false,
        "hasHelmet": false
      }
    },
    {
      "type": "vehicle",
      "id": "2da50ee4-ae70-4c94-88ef-3f4858d63d9e",
      "attributes": {
        "state": "ACTIVE",
        "lastLocationUpdate": "2023-10-07T15:21:45Z",
        "lastStateChange": "2023-10-01T06:38:44Z",
        "batteryLevel": 45,
        "currentRangeMeters": 17000,
        "lat": 52.508331,
        "lng": 13.495889,
        "maxSpeed": 20,
        "zoneId": "BERLIN",
        "code": 281957,
        "iotVendor": "okai",
        "licencePlate": "763WNA",
        "isRentable": true,
        "vehicleType": "escooter",
        "hasHelmetBox": false,
        "hasHelmet": false
      }
    },
    {
      "type": "vehicle",
      "id": "d15a7a6a-49d0-4648-ac46-c24d2c930fcd",
      "attributes": {
        "state": "ACTIVE",
        "lastLocationUpdate": "2023-10-07T15:16:43Z",
        "lastStateChange": "2023-10-04T10:21:32Z",
        "batteryLevel": 76,
        "currentRangeMeters": 33000,
        "lat": 52.508764,
        "lng": 13.497758,
        "maxSpeed": 20,
        "zoneId": "BERLIN",
        "code": 287767,
        "iotVendor": "okai",
        "licencePlate": "234WNA",
        "isRentable": true,
        "vehicleType": "escooter",
        "hasHelmetBox": false,
        "hasHelmet": false
      }
    },
    {
      "type": "vehicle",
      "id": "0f2343b1-3358-4f89-88c9-75639241ce20",
      "attributes": {
        "state": "ACTIVE",
        "lastLocationUpdate": "2023-10-07T14:38:45Z",
        "lastStateChange": "2023-10-05T07:37:48Z",
        "batteryLevel": 75,
        "currentRangeMeters": 33000,
        "lat": 52.510062,
        "lng": 13.498248,
        "maxSpeed": 20,
        "zoneId": "BERLIN",
        "code": 291493,
        "iotVendor": "okai",
        "licencePlate": "766WPO",
        "isRentable": true,
        "vehicleType": "escooter",
        "hasHelmetBox": false,
        "hasHelmet": false
      }
    },
    {
      "type": "vehicle",
      "id": "84c2314a-fdf6-4c19-92c3-1f88f5dbc24a",
      "attributes": {
        "state": "ACTIVE",
        "lastLocationUpdate": "2023-10-07T15:26:44Z",
        "lastStateChange": "2023-10-04T10:27:49Z",
        "batteryLevel": 87,
        "currentRangeMeters": 39000,
        "lat": 52.50881,
        "lng": 13.49622,
        "maxSpeed": 20,
        "zoneId": "BERLIN",
        "code": 295327,
        "iotVendor": "okai",
        "licencePlate": "050WMS",
        "isRentable": true,
        "vehicleType": "escooter",
        "hasHelmetBox": false,
        "hasHelmet": false
      }
    }
  ]
}
